<?xml version="1.0" encoding="UTF-8"?>
<ekidata version="ekidata.jp station_join api 1.0">
	<station_join>
		<station_cd1>1163101</station_cd1>
		<station_cd2>1163102</station_cd2>
		<station_name1>相生</station_name1>
		<station_name2>西相生</station_name2>
		<lat1>34.818052</lat1>
		<lon1>134.47341</lon1>
		<lat2>34.801303</lat2>
		<lon2>134.450563</lon2>
	</station_join>
	<station_join>
		<station_cd1>1163102</station_cd1>
		<station_cd2>1163103</station_cd2>
		<station_name1>西相生</station_name1>
		<station_name2>坂越</station_name2>
		<lat1>34.801303</lat1>
		<lon1>134.450563</lon1>
		<lat2>34.768679</lat2>
		<lon2>134.417244</lon2>
	</station_join>
	<station_join>
		<station_cd1>1163103</station_cd1>
		<station_cd2>1163104</station_cd2>
		<station_name1>坂越</station_name1>
		<station_name2>播州赤穂</station_name2>
		<lat1>34.768679</lat1>
		<lon1>134.417244</lon1>
		<lat2>34.756601</lat2>
		<lon2>134.392976</lon2>
	</station_join>
	<station_join>
		<station_cd1>1163104</station_cd1>
		<station_cd2>1163105</station_cd2>
		<station_name1>播州赤穂</station_name1>
		<station_name2>天和</station_name2>
		<lat1>34.756601</lat1>
		<lon1>134.392976</lon1>
		<lat2>34.749097</lat2>
		<lon2>134.351418</lon2>
	</station_join>
	<station_join>
		<station_cd1>1163105</station_cd1>
		<station_cd2>1163106</station_cd2>
		<station_name1>天和</station_name1>
		<station_name2>備前福河</station_name2>
		<lat1>34.749097</lat1>
		<lon1>134.351418</lon1>
		<lat2>34.746681</lat2>
		<lon2>134.331664</lon2>
	</station_join>
	<station_join>
		<station_cd1>1163106</station_cd1>
		<station_cd2>1163107</station_cd2>
		<station_name1>備前福河</station_name1>
		<station_name2>寒河</station_name2>
		<lat1>34.746681</lat1>
		<lon1>134.331664</lon1>
		<lat2>34.746122</lat2>
		<lon2>134.29778</lon2>
	</station_join>
	<station_join>
		<station_cd1>1163107</station_cd1>
		<station_cd2>1163108</station_cd2>
		<station_name1>寒河</station_name1>
		<station_name2>日生</station_name2>
		<lat1>34.746122</lat1>
		<lon1>134.29778</lon1>
		<lat2>34.735148</lat2>
		<lon2>134.276485</lon2>
	</station_join>
	<station_join>
		<station_cd1>1163108</station_cd1>
		<station_cd2>1163109</station_cd2>
		<station_name1>日生</station_name1>
		<station_name2>伊里</station_name2>
		<lat1>34.735148</lat1>
		<lon1>134.276485</lon1>
		<lat2>34.741424</lat2>
		<lon2>134.224525</lon2>
	</station_join>
	<station_join>
		<station_cd1>1163109</station_cd1>
		<station_cd2>1163110</station_cd2>
		<station_name1>伊里</station_name1>
		<station_name2>備前片上</station_name2>
		<lat1>34.741424</lat1>
		<lon1>134.224525</lon1>
		<lat2>34.748295</lat2>
		<lon2>134.197006</lon2>
	</station_join>
	<station_join>
		<station_cd1>1163110</station_cd1>
		<station_cd2>1163111</station_cd2>
		<station_name1>備前片上</station_name1>
		<station_name2>西片上</station_name2>
		<lat1>34.748295</lat1>
		<lon1>134.197006</lon1>
		<lat2>34.745193</lat2>
		<lon2>134.184177</lon2>
	</station_join>
	<station_join>
		<station_cd1>1163111</station_cd1>
		<station_cd2>1163112</station_cd2>
		<station_name1>西片上</station_name1>
		<station_name2>伊部</station_name2>
		<lat1>34.745193</lat1>
		<lon1>134.184177</lon1>
		<lat2>34.738798</lat2>
		<lon2>134.160554</lon2>
	</station_join>
	<station_join>
		<station_cd1>1163112</station_cd1>
		<station_cd2>1163113</station_cd2>
		<station_name1>伊部</station_name1>
		<station_name2>香登</station_name2>
		<lat1>34.738798</lat1>
		<lon1>134.160554</lon1>
		<lat2>34.727737</lat2>
		<lon2>134.119542</lon2>
	</station_join>
	<station_join>
		<station_cd1>1163113</station_cd1>
		<station_cd2>1163114</station_cd2>
		<station_name1>香登</station_name1>
		<station_name2>長船</station_name2>
		<lat1>34.727737</lat1>
		<lon1>134.119542</lon1>
		<lat2>34.699909</lat2>
		<lon2>134.098828</lon2>
	</station_join>
	<station_join>
		<station_cd1>1163114</station_cd1>
		<station_cd2>1163115</station_cd2>
		<station_name1>長船</station_name1>
		<station_name2>邑久</station_name2>
		<lat1>34.699909</lat1>
		<lon1>134.098828</lon1>
		<lat2>34.668526</lat2>
		<lon2>134.091027</lon2>
	</station_join>
	<station_join>
		<station_cd1>1163115</station_cd1>
		<station_cd2>1163116</station_cd2>
		<station_name1>邑久</station_name1>
		<station_name2>大富</station_name2>
		<lat1>34.668526</lat1>
		<lon1>134.091027</lon1>
		<lat2>34.661429</lat2>
		<lon2>134.070762</lon2>
	</station_join>
	<station_join>
		<station_cd1>1163116</station_cd1>
		<station_cd2>1163117</station_cd2>
		<station_name1>大富</station_name1>
		<station_name2>西大寺</station_name2>
		<lat1>34.661429</lat1>
		<lon1>134.070762</lon1>
		<lat2>34.661878</lat2>
		<lon2>134.037037</lon2>
	</station_join>
	<station_join>
		<station_cd1>1163117</station_cd1>
		<station_cd2>1163118</station_cd2>
		<station_name1>西大寺</station_name1>
		<station_name2>大多羅</station_name2>
		<lat1>34.661878</lat1>
		<lon1>134.037037</lon1>
		<lat2>34.665661</lat2>
		<lon2>134.006354</lon2>
	</station_join>
	<station_join>
		<station_cd1>1163118</station_cd1>
		<station_cd2>1163119</station_cd2>
		<station_name1>大多羅</station_name1>
		<station_name2>東岡山</station_name2>
		<lat1>34.665661</lat1>
		<lon1>134.006354</lon1>
		<lat2>34.685633</lat2>
		<lon2>133.988103</lon2>
	</station_join>
	<station_join>
		<station_cd1>1163119</station_cd1>
		<station_cd2>1163120</station_cd2>
		<station_name1>東岡山</station_name1>
		<station_name2>高島</station_name2>
		<lat1>34.685633</lat1>
		<lon1>133.988103</lon1>
		<lat2>34.683074</lat2>
		<lon2>133.95774</lon2>
	</station_join>
	<station_join>
		<station_cd1>1163120</station_cd1>
		<station_cd2>1163122</station_cd2>
		<station_name1>高島</station_name1>
		<station_name2>西川原</station_name2>
		<lat1>34.683074</lat1>
		<lon1>133.95774</lon1>
		<lat2>34.678</lat2>
		<lon2>133.936555</lon2>
	</station_join>
	<station_join>
		<station_cd1>1163122</station_cd1>
		<station_cd2>1163121</station_cd2>
		<station_name1>西川原</station_name1>
		<station_name2>岡山</station_name2>
		<lat1>34.678</lat1>
		<lon1>133.936555</lon1>
		<lat2>34.666572</lat2>
		<lon2>133.918552</lon2>
	</station_join>
</ekidata>
