{"station_join":[{"station_cd1":2400201,"station_cd2":2400202,"station_name1":"調布","station_name2":"京王多摩川","lat1":35.652181,"lon1":139.543988,"lat2":35.644499,"lon2":139.536606},{"station_cd1":2400202,"station_cd2":2400203,"station_name1":"京王多摩川","station_name2":"京王稲田堤","lat1":35.644499,"lon1":139.536606,"lat2":35.633895,"lon2":139.531099},{"station_cd1":2400203,"station_cd2":2400204,"station_name1":"京王稲田堤","station_name2":"京王よみうりランド","lat1":35.633895,"lon1":139.531099,"lat2":35.632934,"lon2":139.517597},{"station_cd1":2400204,"station_cd2":2400205,"station_name1":"京王よみうりランド","station_name2":"稲城","lat1":35.632934,"lon1":139.517597,"lat2":35.636166,"lon2":139.500398},{"station_cd1":2400205,"station_cd2":2400206,"station_name1":"稲城","station_name2":"若葉台","lat1":35.636166,"lon1":139.500398,"lat2":35.619325,"lon2":139.472189},{"station_cd1":2400206,"station_cd2":2400207,"station_name1":"若葉台","station_name2":"京王永山","lat1":35.619325,"lon1":139.472189,"lat2":35.630102,"lon2":139.448204},{"station_cd1":2400207,"station_cd2":2400208,"station_name1":"京王永山","station_name2":"京王多摩センター","lat1":35.630102,"lon1":139.448204,"lat2":35.62518,"lon2":139.42402},{"station_cd1":2400208,"station_cd2":2400209,"station_name1":"京王多摩センター","station_name2":"京王堀之内","lat1":35.62518,"lon1":139.42402,"lat2":35.624438,"lon2":139.400314},{"station_cd1":2400209,"station_cd2":2400210,"station_name1":"京王堀之内","station_name2":"南大沢","lat1":35.624438,"lon1":139.400314,"lat2":35.6141,"lon2":139.3798},{"station_cd1":2400210,"station_cd2":2400211,"station_name1":"南大沢","station_name2":"多摩境","lat1":35.6141,"lon1":139.3798,"lat2":35.601826,"lon2":139.366987},{"station_cd1":2400211,"station_cd2":2400212,"station_name1":"多摩境","station_name2":"橋本","lat1":35.601826,"lon1":139.366987,"lat2":35.595518,"lon2":139.343226}]}
