{"station_join":[{"station_cd1":9930501,"station_cd2":9930502,"station_name1":"三ノ輪橋","station_name2":"荒川一中前","lat1":35.732248,"lon1":139.791412,"lat2":35.733659,"lon2":139.788988},{"station_cd1":9930502,"station_cd2":9930503,"station_name1":"荒川一中前","station_name2":"荒川区役所前","lat1":35.733659,"lon1":139.788988,"lat2":35.73493,"lon2":139.786456},{"station_cd1":9930503,"station_cd2":9930504,"station_name1":"荒川区役所前","station_name2":"荒川二丁目","lat1":35.73493,"lon1":139.786456,"lat2":35.738623,"lon2":139.784696},{"station_cd1":9930504,"station_cd2":9930505,"station_name1":"荒川二丁目","station_name2":"荒川七丁目","lat1":35.738623,"lon1":139.784696,"lat2":35.741975,"lon2":139.78417},{"station_cd1":9930505,"station_cd2":9930506,"station_name1":"荒川七丁目","station_name2":"町屋駅前","lat1":35.741975,"lon1":139.78417,"lat2":35.74275,"lon2":139.781145},{"station_cd1":9930506,"station_cd2":9930507,"station_name1":"町屋駅前","station_name2":"町屋二丁目","lat1":35.74275,"lon1":139.781145,"lat2":35.743837,"lon2":139.776625},{"station_cd1":9930507,"station_cd2":9930508,"station_name1":"町屋二丁目","station_name2":"東尾久三丁目","lat1":35.743837,"lon1":139.776625,"lat2":35.745398,"lon2":139.774386},{"station_cd1":9930508,"station_cd2":9930509,"station_name1":"東尾久三丁目","station_name2":"熊野前","lat1":35.745398,"lon1":139.774386,"lat2":35.749212,"lon2":139.769204},{"station_cd1":9930509,"station_cd2":9930510,"station_name1":"熊野前","station_name2":"宮ノ前","lat1":35.749212,"lon1":139.769204,"lat2":35.750135,"lon2":139.764955},{"station_cd1":9930510,"station_cd2":9930511,"station_name1":"宮ノ前","station_name2":"小台","lat1":35.750135,"lon1":139.764955,"lat2":35.750579,"lon2":139.761779},{"station_cd1":9930511,"station_cd2":9930512,"station_name1":"小台","station_name2":"荒川遊園地前","lat1":35.750579,"lon1":139.761779,"lat2":35.750744,"lon2":139.757767},{"station_cd1":9930512,"station_cd2":9930513,"station_name1":"荒川遊園地前","station_name2":"荒川車庫前","lat1":35.750744,"lon1":139.757767,"lat2":35.750909,"lon2":139.752617},{"station_cd1":9930513,"station_cd2":9930514,"station_name1":"荒川車庫前","station_name2":"梶原","lat1":35.750909,"lon1":139.752617,"lat2":35.751162,"lon2":139.747403},{"station_cd1":9930514,"station_cd2":9930515,"station_name1":"梶原","station_name2":"栄町","lat1":35.751162,"lon1":139.747403,"lat2":35.750909,"lon2":139.742124},{"station_cd1":9930515,"station_cd2":9930516,"station_name1":"栄町","station_name2":"王子駅前","lat1":35.750909,"lon1":139.742124,"lat2":35.753199,"lon2":139.737661},{"station_cd1":9930516,"station_cd2":9930517,"station_name1":"王子駅前","station_name2":"飛鳥山","lat1":35.753199,"lon1":139.737661,"lat2":35.750248,"lon2":139.737382},{"station_cd1":9930517,"station_cd2":9930518,"station_name1":"飛鳥山","station_name2":"滝野川一丁目","lat1":35.750248,"lon1":139.737382,"lat2":35.747374,"lon2":139.735376},{"station_cd1":9930518,"station_cd2":9930519,"station_name1":"滝野川一丁目","station_name2":"西ヶ原四丁目","lat1":35.747374,"lon1":139.735376,"lat2":35.744501,"lon2":139.732779},{"station_cd1":9930519,"station_cd2":9930520,"station_name1":"西ヶ原四丁目","station_name2":"新庚申塚","lat1":35.744501,"lon1":139.732779,"lat2":35.741348,"lon2":139.730451},{"station_cd1":9930520,"station_cd2":9930521,"station_name1":"新庚申塚","station_name2":"庚申塚","lat1":35.741348,"lon1":139.730451,"lat2":35.739563,"lon2":139.729743},{"station_cd1":9930521,"station_cd2":9930522,"station_name1":"庚申塚","station_name2":"巣鴨新田","lat1":35.739563,"lon1":139.729743,"lat2":35.735488,"lon2":139.727769},{"station_cd1":9930522,"station_cd2":9930523,"station_name1":"巣鴨新田","station_name2":"大塚駅前","lat1":35.735488,"lon1":139.727769,"lat2":35.732082,"lon2":139.729593},{"station_cd1":9930523,"station_cd2":9930524,"station_name1":"大塚駅前","station_name2":"向原","lat1":35.732082,"lon1":139.729593,"lat2":35.728938,"lon2":139.724894},{"station_cd1":9930524,"station_cd2":9930525,"station_name1":"向原","station_name2":"東池袋四丁目","lat1":35.728938,"lon1":139.724894,"lat2":35.72528,"lon2":139.720012},{"station_cd1":9930525,"station_cd2":9930526,"station_name1":"東池袋四丁目","station_name2":"都電雑司ヶ谷","lat1":35.72528,"lon1":139.720012,"lat2":35.724261,"lon2":139.718006},{"station_cd1":9930526,"station_cd2":9930527,"station_name1":"都電雑司ヶ谷","station_name2":"鬼子母神前","lat1":35.724261,"lon1":139.718006,"lat2":35.720403,"lon2":139.714916},{"station_cd1":9930527,"station_cd2":9930528,"station_name1":"鬼子母神前","station_name2":"学習院下","lat1":35.720403,"lon1":139.714916,"lat2":35.716248,"lon2":139.71247},{"station_cd1":9930528,"station_cd2":9930529,"station_name1":"学習院下","station_name2":"面影橋","lat1":35.716248,"lon1":139.71247,"lat2":35.712981,"lon2":139.714444},{"station_cd1":9930529,"station_cd2":9930530,"station_name1":"面影橋","station_name2":"早稲田","lat1":35.712981,"lon1":139.714444,"lat2":35.711848,"lon2":139.718928}]}
