<?xml version="1.0" encoding="UTF-8"?>
<ekidata version="ekidata.jp station_join api 1.0">
	<station_join>
		<station_cd1>9933501</station_cd1>
		<station_cd2>9933502</station_cd2>
		<station_name1>銚子</station_name1>
		<station_name2>仲ノ町</station_name2>
		<lat1>35.729449</lat1>
		<lon1>140.827557</lon1>
		<lat2>35.728813</lat2>
		<lon2>140.833871</lon2>
	</station_join>
	<station_join>
		<station_cd1>9933502</station_cd1>
		<station_cd2>9933503</station_cd2>
		<station_name1>仲ノ町</station_name1>
		<station_name2>観音</station_name2>
		<lat1>35.728813</lat1>
		<lon1>140.833871</lon1>
		<lat2>35.728952</lat2>
		<lon2>140.840112</lon2>
	</station_join>
	<station_join>
		<station_cd1>9933503</station_cd1>
		<station_cd2>9933504</station_cd2>
		<station_name1>観音</station_name1>
		<station_name2>本銚子</station_name2>
		<lat1>35.728952</lat1>
		<lon1>140.840112</lon1>
		<lat2>35.731055</lat2>
		<lon2>140.847844</lon2>
	</station_join>
	<station_join>
		<station_cd1>9933504</station_cd1>
		<station_cd2>9933505</station_cd2>
		<station_name1>本銚子</station_name1>
		<station_name2>笠上黒生</station_name2>
		<lat1>35.731055</lat1>
		<lon1>140.847844</lon1>
		<lat2>35.728427</lat2>
		<lon2>140.856893</lon2>
	</station_join>
	<station_join>
		<station_cd1>9933505</station_cd1>
		<station_cd2>9933506</station_cd2>
		<station_name1>笠上黒生</station_name1>
		<station_name2>西海鹿島</station_name2>
		<lat1>35.728427</lat1>
		<lon1>140.856893</lon1>
		<lat2>35.725131</lat2>
		<lon2>140.860207</lon2>
	</station_join>
	<station_join>
		<station_cd1>9933506</station_cd1>
		<station_cd2>9933507</station_cd2>
		<station_name1>西海鹿島</station_name1>
		<station_name2>海鹿島</station_name2>
		<lat1>35.725131</lat1>
		<lon1>140.860207</lon1>
		<lat2>35.722089</lat2>
		<lon2>140.863096</lon2>
	</station_join>
	<station_join>
		<station_cd1>9933507</station_cd1>
		<station_cd2>9933508</station_cd2>
		<station_name1>海鹿島</station_name1>
		<station_name2>君ヶ浜</station_name2>
		<lat1>35.722089</lat1>
		<lon1>140.863096</lon1>
		<lat2>35.714093</lat2>
		<lon2>140.860527</lon2>
	</station_join>
	<station_join>
		<station_cd1>9933508</station_cd1>
		<station_cd2>9933509</station_cd2>
		<station_name1>君ヶ浜</station_name1>
		<station_name2>犬吠</station_name2>
		<lat1>35.714093</lat1>
		<lon1>140.860527</lon1>
		<lat2>35.706258</lat2>
		<lon2>140.860935</lon2>
	</station_join>
	<station_join>
		<station_cd1>9933509</station_cd1>
		<station_cd2>9933510</station_cd2>
		<station_name1>犬吠</station_name1>
		<station_name2>外川</station_name2>
		<lat1>35.706258</lat1>
		<lon1>140.860935</lon1>
		<lat2>35.699314</lat2>
		<lon2>140.857322</lon2>
	</station_join>
</ekidata>
