<?xml version="1.0" encoding="UTF-8"?>
<ekidata version="ekidata.jp line api 1.0">
	<line>
		<line_cd>99341</line_cd>
		<line_name>ほっとスパ・ライン</line_name>
		<line_lon>139.70133274067</line_lon>
		<line_lat>36.987335574449</line_lat>
		<line_zoom>11</line_zoom>
	</line>
	<station>
		<station_cd>9934101</station_cd>
		<station_g_cd>2100908</station_g_cd>
		<station_name>新藤原</station_name>
		<lon>139.732963</lon>
		<lat>36.852505</lat>
	</station>
	<station>
		<station_cd>9934102</station_cd>
		<station_g_cd>9934102</station_g_cd>
		<station_name>龍王峡</station_name>
		<lon>139.718542</lon>
		<lat>36.860909</lat>
	</station>
	<station>
		<station_cd>9934103</station_cd>
		<station_g_cd>9934103</station_g_cd>
		<station_name>川治温泉</station_name>
		<lon>139.703775</lon>
		<lat>36.884036</lat>
	</station>
	<station>
		<station_cd>9934104</station_cd>
		<station_g_cd>9934104</station_g_cd>
		<station_name>川治湯元</station_name>
		<lon>139.702772</lon>
		<lat>36.895126</lat>
	</station>
	<station>
		<station_cd>9934105</station_cd>
		<station_g_cd>9934105</station_g_cd>
		<station_name>湯西川温泉</station_name>
		<lon>139.68824</lon>
		<lat>36.929482</lat>
	</station>
	<station>
		<station_cd>9934106</station_cd>
		<station_g_cd>9934106</station_g_cd>
		<station_name>中三依温泉</station_name>
		<lon>139.69614</lon>
		<lat>36.985843</lat>
	</station>
	<station>
		<station_cd>9934107</station_cd>
		<station_g_cd>9934107</station_g_cd>
		<station_name>上三依塩原温泉口</station_name>
		<lon>139.727168</lon>
		<lat>37.014461</lat>
	</station>
	<station>
		<station_cd>9934108</station_cd>
		<station_g_cd>9934108</station_g_cd>
		<station_name>男鹿高原</station_name>
		<lon>139.723845</lon>
		<lat>37.04784</lat>
	</station>
	<station>
		<station_cd>9934109</station_cd>
		<station_g_cd>9921621</station_g_cd>
		<station_name>会津高原尾瀬口</station_name>
		<lon>139.705067</lon>
		<lat>37.089949</lat>
	</station>
</ekidata>
