<?xml version="1.0" encoding="UTF-8"?>
<ekidata version="ekidata.jp station_join api 1.0">
	<station_join>
		<station_cd1>1121001</station_cd1>
		<station_cd2>1121002</station_cd2>
		<station_name1>北上</station_name1>
		<station_name2>柳原</station_name2>
		<lat1>39.281196</lat1>
		<lon1>141.121221</lon1>
		<lat2>39.294597</lat2>
		<lon2>141.111671</lon2>
	</station_join>
	<station_join>
		<station_cd1>1121002</station_cd1>
		<station_cd2>1121003</station_cd2>
		<station_name1>柳原</station_name1>
		<station_name2>江釣子</station_name2>
		<lat1>39.294597</lat1>
		<lon1>141.111671</lon1>
		<lat2>39.298349</lat2>
		<lon2>141.075749</lon2>
	</station_join>
	<station_join>
		<station_cd1>1121003</station_cd1>
		<station_cd2>1121004</station_cd2>
		<station_name1>江釣子</station_name1>
		<station_name2>藤根</station_name2>
		<lat1>39.298349</lat1>
		<lon1>141.075749</lon1>
		<lat2>39.301064</lat2>
		<lon2>141.039571</lon2>
	</station_join>
	<station_join>
		<station_cd1>1121004</station_cd1>
		<station_cd2>1121005</station_cd2>
		<station_name1>藤根</station_name1>
		<station_name2>立川目</station_name2>
		<lat1>39.301064</lat1>
		<lon1>141.039571</lon1>
		<lat2>39.307876</lat2>
		<lon2>140.997144</lon2>
	</station_join>
	<station_join>
		<station_cd1>1121005</station_cd1>
		<station_cd2>1121006</station_cd2>
		<station_name1>立川目</station_name1>
		<station_name2>横川目</station_name2>
		<lat1>39.307876</lat1>
		<lon1>140.997144</lon1>
		<lat2>39.309255</lat2>
		<lon2>140.972143</lon2>
	</station_join>
	<station_join>
		<station_cd1>1121006</station_cd1>
		<station_cd2>1121007</station_cd2>
		<station_name1>横川目</station_name1>
		<station_name2>岩沢</station_name2>
		<lat1>39.309255</lat1>
		<lon1>140.972143</lon1>
		<lat2>39.301016</lat2>
		<lon2>140.931616</lon2>
	</station_join>
	<station_join>
		<station_cd1>1121007</station_cd1>
		<station_cd2>1121008</station_cd2>
		<station_name1>岩沢</station_name1>
		<station_name2>和賀仙人</station_name2>
		<lat1>39.301016</lat1>
		<lon1>140.931616</lon1>
		<lat2>39.308523</lat2>
		<lon2>140.909485</lon2>
	</station_join>
	<station_join>
		<station_cd1>1121008</station_cd1>
		<station_cd2>1121009</station_cd2>
		<station_name1>和賀仙人</station_name1>
		<station_name2>ゆだ錦秋湖</station_name2>
		<lat1>39.308523</lat1>
		<lon1>140.909485</lon1>
		<lat2>39.295513</lat2>
		<lon2>140.835343</lon2>
	</station_join>
	<station_join>
		<station_cd1>1121009</station_cd1>
		<station_cd2>1121010</station_cd2>
		<station_name1>ゆだ錦秋湖</station_name1>
		<station_name2>ほっとゆだ</station_name2>
		<lat1>39.295513</lat1>
		<lon1>140.835343</lon1>
		<lat2>39.314493</lat2>
		<lon2>140.775647</lon2>
	</station_join>
	<station_join>
		<station_cd1>1121010</station_cd1>
		<station_cd2>1121011</station_cd2>
		<station_name1>ほっとゆだ</station_name1>
		<station_name2>ゆだ高原</station_name2>
		<lat1>39.314493</lat1>
		<lon1>140.775647</lon1>
		<lat2>39.301074</lat2>
		<lon2>140.737205</lon2>
	</station_join>
	<station_join>
		<station_cd1>1121011</station_cd1>
		<station_cd2>1121012</station_cd2>
		<station_name1>ゆだ高原</station_name1>
		<station_name2>黒沢</station_name2>
		<lat1>39.301074</lat1>
		<lon1>140.737205</lon1>
		<lat2>39.276243</lat2>
		<lon2>140.699619</lon2>
	</station_join>
	<station_join>
		<station_cd1>1121012</station_cd1>
		<station_cd2>1121013</station_cd2>
		<station_name1>黒沢</station_name1>
		<station_name2>小松川</station_name2>
		<lat1>39.276243</lat1>
		<lon1>140.699619</lon1>
		<lat2>39.293403</lat2>
		<lon2>140.646094</lon2>
	</station_join>
	<station_join>
		<station_cd1>1121013</station_cd1>
		<station_cd2>1121014</station_cd2>
		<station_name1>小松川</station_name1>
		<station_name2>平石</station_name2>
		<lat1>39.293403</lat1>
		<lon1>140.646094</lon1>
		<lat2>39.291678</lat2>
		<lon2>140.628457</lon2>
	</station_join>
	<station_join>
		<station_cd1>1121014</station_cd1>
		<station_cd2>1121015</station_cd2>
		<station_name1>平石</station_name1>
		<station_name2>相野々</station_name2>
		<lat1>39.291678</lat1>
		<lon1>140.628457</lon1>
		<lat2>39.27805</lat2>
		<lon2>140.619067</lon2>
	</station_join>
	<station_join>
		<station_cd1>1121015</station_cd1>
		<station_cd2>1121016</station_cd2>
		<station_name1>相野々</station_name1>
		<station_name2>矢美津</station_name2>
		<lat1>39.27805</lat1>
		<lon1>140.619067</lon1>
		<lat2>39.291283</lat2>
		<lon2>140.592099</lon2>
	</station_join>
	<station_join>
		<station_cd1>1121016</station_cd1>
		<station_cd2>1121017</station_cd2>
		<station_name1>矢美津</station_name1>
		<station_name2>横手</station_name2>
		<lat1>39.291283</lat1>
		<lon1>140.592099</lon1>
		<lat2>39.310146</lat2>
		<lon2>140.5604</lon2>
	</station_join>
</ekidata>
