<?xml version="1.0" encoding="UTF-8"?>
<ekidata version="ekidata.jp station_join api 1.0">
	<station_join>
		<station_cd1>1133201</station_cd1>
		<station_cd2>1133202</station_cd2>
		<station_name1>大宮</station_name1>
		<station_name2>さいたま新都心</station_name2>
		<lat1>35.906439</lat1>
		<lon1>139.62405</lon1>
		<lat2>35.893867</lat2>
		<lon2>139.633587</lon2>
	</station_join>
	<station_join>
		<station_cd1>1133202</station_cd1>
		<station_cd2>1133203</station_cd2>
		<station_name1>さいたま新都心</station_name1>
		<station_name2>与野</station_name2>
		<lat1>35.893867</lat1>
		<lon1>139.633587</lon1>
		<lat2>35.884393</lat2>
		<lon2>139.639085</lon2>
	</station_join>
	<station_join>
		<station_cd1>1133203</station_cd1>
		<station_cd2>1133204</station_cd2>
		<station_name1>与野</station_name1>
		<station_name2>北浦和</station_name2>
		<lat1>35.884393</lat1>
		<lon1>139.639085</lon1>
		<lat2>35.872053</lat2>
		<lon2>139.645951</lon2>
	</station_join>
	<station_join>
		<station_cd1>1133204</station_cd1>
		<station_cd2>1133205</station_cd2>
		<station_name1>北浦和</station_name1>
		<station_name2>浦和</station_name2>
		<lat1>35.872053</lat1>
		<lon1>139.645951</lon1>
		<lat2>35.858496</lat2>
		<lon2>139.657109</lon2>
	</station_join>
	<station_join>
		<station_cd1>1133205</station_cd1>
		<station_cd2>1133206</station_cd2>
		<station_name1>浦和</station_name1>
		<station_name2>南浦和</station_name2>
		<lat1>35.858496</lat1>
		<lon1>139.657109</lon1>
		<lat2>35.847648</lat2>
		<lon2>139.669125</lon2>
	</station_join>
	<station_join>
		<station_cd1>1133206</station_cd1>
		<station_cd2>1133207</station_cd2>
		<station_name1>南浦和</station_name1>
		<station_name2>蕨</station_name2>
		<lat1>35.847648</lat1>
		<lon1>139.669125</lon1>
		<lat2>35.827959</lat2>
		<lon2>139.690357</lon2>
	</station_join>
	<station_join>
		<station_cd1>1133207</station_cd1>
		<station_cd2>1133208</station_cd2>
		<station_name1>蕨</station_name1>
		<station_name2>西川口</station_name2>
		<lat1>35.827959</lat1>
		<lon1>139.690357</lon1>
		<lat2>35.815514</lat2>
		<lon2>139.704312</lon2>
	</station_join>
	<station_join>
		<station_cd1>1133208</station_cd1>
		<station_cd2>1133209</station_cd2>
		<station_name1>西川口</station_name1>
		<station_name2>川口</station_name2>
		<lat1>35.815514</lat1>
		<lon1>139.704312</lon1>
		<lat2>35.801869</lat2>
		<lon2>139.717472</lon2>
	</station_join>
	<station_join>
		<station_cd1>1133209</station_cd1>
		<station_cd2>1133210</station_cd2>
		<station_name1>川口</station_name1>
		<station_name2>赤羽</station_name2>
		<lat1>35.801869</lat1>
		<lon1>139.717472</lon1>
		<lat2>35.778026</lat2>
		<lon2>139.720928</lon2>
	</station_join>
	<station_join>
		<station_cd1>1133210</station_cd1>
		<station_cd2>1133211</station_cd2>
		<station_name1>赤羽</station_name1>
		<station_name2>東十条</station_name2>
		<lat1>35.778026</lat1>
		<lon1>139.720928</lon1>
		<lat2>35.763803</lat2>
		<lon2>139.726858</lon2>
	</station_join>
	<station_join>
		<station_cd1>1133211</station_cd1>
		<station_cd2>1133212</station_cd2>
		<station_name1>東十条</station_name1>
		<station_name2>王子</station_name2>
		<lat1>35.763803</lat1>
		<lon1>139.726858</lon1>
		<lat2>35.752538</lat2>
		<lon2>139.73809</lon2>
	</station_join>
	<station_join>
		<station_cd1>1133212</station_cd1>
		<station_cd2>1133213</station_cd2>
		<station_name1>王子</station_name1>
		<station_name2>上中里</station_name2>
		<lat1>35.752538</lat1>
		<lon1>139.73809</lon1>
		<lat2>35.74728</lat2>
		<lon2>139.745769</lon2>
	</station_join>
	<station_join>
		<station_cd1>1133213</station_cd1>
		<station_cd2>1133214</station_cd2>
		<station_name1>上中里</station_name1>
		<station_name2>田端</station_name2>
		<lat1>35.74728</lat1>
		<lon1>139.745769</lon1>
		<lat2>35.737781</lat2>
		<lon2>139.761229</lon2>
	</station_join>
	<station_join>
		<station_cd1>1133214</station_cd1>
		<station_cd2>1133215</station_cd2>
		<station_name1>田端</station_name1>
		<station_name2>西日暮里</station_name2>
		<lat1>35.737781</lat1>
		<lon1>139.761229</lon1>
		<lat2>35.731954</lat2>
		<lon2>139.766857</lon2>
	</station_join>
	<station_join>
		<station_cd1>1133215</station_cd1>
		<station_cd2>1133216</station_cd2>
		<station_name1>西日暮里</station_name1>
		<station_name2>日暮里</station_name2>
		<lat1>35.731954</lat1>
		<lon1>139.766857</lon1>
		<lat2>35.727908</lat2>
		<lon2>139.771287</lon2>
	</station_join>
	<station_join>
		<station_cd1>1133216</station_cd1>
		<station_cd2>1133217</station_cd2>
		<station_name1>日暮里</station_name1>
		<station_name2>鶯谷</station_name2>
		<lat1>35.727908</lat1>
		<lon1>139.771287</lon1>
		<lat2>35.721484</lat2>
		<lon2>139.778015</lon2>
	</station_join>
	<station_join>
		<station_cd1>1133217</station_cd1>
		<station_cd2>1133218</station_cd2>
		<station_name1>鶯谷</station_name1>
		<station_name2>上野</station_name2>
		<lat1>35.721484</lat1>
		<lon1>139.778015</lon1>
		<lat2>35.71379</lat2>
		<lon2>139.777043</lon2>
	</station_join>
	<station_join>
		<station_cd1>1133218</station_cd1>
		<station_cd2>1133219</station_cd2>
		<station_name1>上野</station_name1>
		<station_name2>御徒町</station_name2>
		<lat1>35.71379</lat1>
		<lon1>139.777043</lon1>
		<lat2>35.707282</lat2>
		<lon2>139.774727</lon2>
	</station_join>
	<station_join>
		<station_cd1>1133219</station_cd1>
		<station_cd2>1133220</station_cd2>
		<station_name1>御徒町</station_name1>
		<station_name2>秋葉原</station_name2>
		<lat1>35.707282</lat1>
		<lon1>139.774727</lon1>
		<lat2>35.698619</lat2>
		<lon2>139.773288</lon2>
	</station_join>
	<station_join>
		<station_cd1>1133220</station_cd1>
		<station_cd2>1133221</station_cd2>
		<station_name1>秋葉原</station_name1>
		<station_name2>神田</station_name2>
		<lat1>35.698619</lat1>
		<lon1>139.773288</lon1>
		<lat2>35.691173</lat2>
		<lon2>139.770641</lon2>
	</station_join>
	<station_join>
		<station_cd1>1133221</station_cd1>
		<station_cd2>1133222</station_cd2>
		<station_name1>神田</station_name1>
		<station_name2>東京</station_name2>
		<lat1>35.691173</lat1>
		<lon1>139.770641</lon1>
		<lat2>35.681391</lat2>
		<lon2>139.766103</lon2>
	</station_join>
	<station_join>
		<station_cd1>1133222</station_cd1>
		<station_cd2>1133223</station_cd2>
		<station_name1>東京</station_name1>
		<station_name2>有楽町</station_name2>
		<lat1>35.681391</lat1>
		<lon1>139.766103</lon1>
		<lat2>35.675441</lat2>
		<lon2>139.763806</lon2>
	</station_join>
	<station_join>
		<station_cd1>1133223</station_cd1>
		<station_cd2>1133224</station_cd2>
		<station_name1>有楽町</station_name1>
		<station_name2>新橋</station_name2>
		<lat1>35.675441</lat1>
		<lon1>139.763806</lon1>
		<lat2>35.666195</lat2>
		<lon2>139.758587</lon2>
	</station_join>
	<station_join>
		<station_cd1>1133224</station_cd1>
		<station_cd2>1133225</station_cd2>
		<station_name1>新橋</station_name1>
		<station_name2>浜松町</station_name2>
		<lat1>35.666195</lat1>
		<lon1>139.758587</lon1>
		<lat2>35.655391</lat2>
		<lon2>139.757135</lon2>
	</station_join>
	<station_join>
		<station_cd1>1133225</station_cd1>
		<station_cd2>1133226</station_cd2>
		<station_name1>浜松町</station_name1>
		<station_name2>田町</station_name2>
		<lat1>35.655391</lat1>
		<lon1>139.757135</lon1>
		<lat2>35.645736</lat2>
		<lon2>139.747575</lon2>
	</station_join>
	<station_join>
		<station_cd1>1133226</station_cd1>
		<station_cd2>1133227</station_cd2>
		<station_name1>田町</station_name1>
		<station_name2>品川</station_name2>
		<lat1>35.645736</lat1>
		<lon1>139.747575</lon1>
		<lat2>35.62876</lat2>
		<lon2>139.738999</lon2>
	</station_join>
	<station_join>
		<station_cd1>1133227</station_cd1>
		<station_cd2>1133228</station_cd2>
		<station_name1>品川</station_name1>
		<station_name2>大井町</station_name2>
		<lat1>35.62876</lat1>
		<lon1>139.738999</lon1>
		<lat2>35.606257</lat2>
		<lon2>139.73485</lon2>
	</station_join>
	<station_join>
		<station_cd1>1133228</station_cd1>
		<station_cd2>1133229</station_cd2>
		<station_name1>大井町</station_name1>
		<station_name2>大森</station_name2>
		<lat1>35.606257</lat1>
		<lon1>139.73485</lon1>
		<lat2>35.588903</lat2>
		<lon2>139.728079</lon2>
	</station_join>
	<station_join>
		<station_cd1>1133229</station_cd1>
		<station_cd2>1133230</station_cd2>
		<station_name1>大森</station_name1>
		<station_name2>蒲田</station_name2>
		<lat1>35.588903</lat1>
		<lon1>139.728079</lon1>
		<lat2>35.562517</lat2>
		<lon2>139.716032</lon2>
	</station_join>
	<station_join>
		<station_cd1>1133230</station_cd1>
		<station_cd2>1133231</station_cd2>
		<station_name1>蒲田</station_name1>
		<station_name2>川崎</station_name2>
		<lat1>35.562517</lat1>
		<lon1>139.716032</lon1>
		<lat2>35.531311</lat2>
		<lon2>139.697485</lon2>
	</station_join>
	<station_join>
		<station_cd1>1133231</station_cd1>
		<station_cd2>1133232</station_cd2>
		<station_name1>川崎</station_name1>
		<station_name2>鶴見</station_name2>
		<lat1>35.531311</lat1>
		<lon1>139.697485</lon1>
		<lat2>35.508387</lat2>
		<lon2>139.67614</lon2>
	</station_join>
	<station_join>
		<station_cd1>1133232</station_cd1>
		<station_cd2>1133233</station_cd2>
		<station_name1>鶴見</station_name1>
		<station_name2>新子安</station_name2>
		<lat1>35.508387</lat1>
		<lon1>139.67614</lon1>
		<lat2>35.487064</lat2>
		<lon2>139.654776</lon2>
	</station_join>
	<station_join>
		<station_cd1>1133233</station_cd1>
		<station_cd2>1133234</station_cd2>
		<station_name1>新子安</station_name1>
		<station_name2>東神奈川</station_name2>
		<lat1>35.487064</lat1>
		<lon1>139.654776</lon1>
		<lat2>35.47804</lat2>
		<lon2>139.633466</lon2>
	</station_join>
	<station_join>
		<station_cd1>1133234</station_cd1>
		<station_cd2>1133235</station_cd2>
		<station_name1>東神奈川</station_name1>
		<station_name2>横浜</station_name2>
		<lat1>35.47804</lat1>
		<lon1>139.633466</lon1>
		<lat2>35.466195</lat2>
		<lon2>139.622704</lon2>
	</station_join>
</ekidata>
