<?xml version="1.0" encoding="UTF-8"?>
<ekidata version="ekidata.jp station_join api 1.0">
	<station_join>
		<station_cd1>3300101</station_cd1>
		<station_cd2>3300102</station_cd2>
		<station_name1>三条</station_name1>
		<station_name2>祇園四条</station_name2>
		<lat1>35.009114</lat1>
		<lon1>135.772274</lon1>
		<lat2>35.003689</lat2>
		<lon2>135.771961</lon2>
	</station_join>
	<station_join>
		<station_cd1>3300102</station_cd1>
		<station_cd2>3300103</station_cd2>
		<station_name1>祇園四条</station_name1>
		<station_name2>清水五条</station_name2>
		<lat1>35.003689</lat1>
		<lon1>135.771961</lon1>
		<lat2>34.995691</lat2>
		<lon2>135.768378</lon2>
	</station_join>
	<station_join>
		<station_cd1>3300103</station_cd1>
		<station_cd2>3300104</station_cd2>
		<station_name1>清水五条</station_name1>
		<station_name2>七条</station_name2>
		<lat1>34.995691</lat1>
		<lon1>135.768378</lon1>
		<lat2>34.989322</lat2>
		<lon2>135.767846</lon2>
	</station_join>
	<station_join>
		<station_cd1>3300104</station_cd1>
		<station_cd2>3300105</station_cd2>
		<station_name1>七条</station_name1>
		<station_name2>東福寺</station_name2>
		<lat1>34.989322</lat1>
		<lon1>135.767846</lon1>
		<lat2>34.981351</lat2>
		<lon2>135.769998</lon2>
	</station_join>
	<station_join>
		<station_cd1>3300105</station_cd1>
		<station_cd2>3300106</station_cd2>
		<station_name1>東福寺</station_name1>
		<station_name2>鳥羽街道</station_name2>
		<lat1>34.981351</lat1>
		<lon1>135.769998</lon1>
		<lat2>34.973632</lat2>
		<lon2>135.770004</lon2>
	</station_join>
	<station_join>
		<station_cd1>3300106</station_cd1>
		<station_cd2>3300107</station_cd2>
		<station_name1>鳥羽街道</station_name1>
		<station_name2>伏見稲荷</station_name2>
		<lat1>34.973632</lat1>
		<lon1>135.770004</lon1>
		<lat2>34.968966</lat2>
		<lon2>135.769279</lon2>
	</station_join>
	<station_join>
		<station_cd1>3300107</station_cd1>
		<station_cd2>3300108</station_cd2>
		<station_name1>伏見稲荷</station_name1>
		<station_name2>龍谷大前深草</station_name2>
		<lat1>34.968966</lat1>
		<lon1>135.769279</lon1>
		<lat2>34.964247</lat2>
		<lon2>135.770154</lon2>
	</station_join>
	<station_join>
		<station_cd1>3300108</station_cd1>
		<station_cd2>3300109</station_cd2>
		<station_name1>龍谷大前深草</station_name1>
		<station_name2>藤森</station_name2>
		<lat1>34.964247</lat1>
		<lon1>135.770154</lon1>
		<lat2>34.956782</lat2>
		<lon2>135.770191</lon2>
	</station_join>
	<station_join>
		<station_cd1>3300109</station_cd1>
		<station_cd2>3300110</station_cd2>
		<station_name1>藤森</station_name1>
		<station_name2>墨染</station_name2>
		<lat1>34.956782</lat1>
		<lon1>135.770191</lon1>
		<lat2>34.948206</lat2>
		<lon2>135.769126</lon2>
	</station_join>
	<station_join>
		<station_cd1>3300110</station_cd1>
		<station_cd2>3300111</station_cd2>
		<station_name1>墨染</station_name1>
		<station_name2>丹波橋</station_name2>
		<lat1>34.948206</lat1>
		<lon1>135.769126</lon1>
		<lat2>34.938879</lat2>
		<lon2>135.765457</lon2>
	</station_join>
	<station_join>
		<station_cd1>3300111</station_cd1>
		<station_cd2>3300112</station_cd2>
		<station_name1>丹波橋</station_name1>
		<station_name2>伏見桃山</station_name2>
		<lat1>34.938879</lat1>
		<lon1>135.765457</lon1>
		<lat2>34.932599</lat2>
		<lon2>135.764368</lon2>
	</station_join>
	<station_join>
		<station_cd1>3300112</station_cd1>
		<station_cd2>3300113</station_cd2>
		<station_name1>伏見桃山</station_name1>
		<station_name2>中書島</station_name2>
		<lat1>34.932599</lat1>
		<lon1>135.764368</lon1>
		<lat2>34.926875</lat2>
		<lon2>135.760174</lon2>
	</station_join>
	<station_join>
		<station_cd1>3300113</station_cd1>
		<station_cd2>3300114</station_cd2>
		<station_name1>中書島</station_name1>
		<station_name2>淀</station_name2>
		<lat1>34.926875</lat1>
		<lon1>135.760174</lon1>
		<lat2>34.904416</lat2>
		<lon2>135.718435</lon2>
	</station_join>
	<station_join>
		<station_cd1>3300114</station_cd1>
		<station_cd2>3300115</station_cd2>
		<station_name1>淀</station_name1>
		<station_name2>石清水八幡宮</station_name2>
		<lat1>34.904416</lat1>
		<lon1>135.718435</lon1>
		<lat2>34.884651</lat2>
		<lon2>135.69996</lon2>
	</station_join>
	<station_join>
		<station_cd1>3300115</station_cd1>
		<station_cd2>3300116</station_cd2>
		<station_name1>石清水八幡宮</station_name1>
		<station_name2>橋本</station_name2>
		<lat1>34.884651</lat1>
		<lon1>135.69996</lon1>
		<lat2>34.882042</lat2>
		<lon2>135.684251</lon2>
	</station_join>
	<station_join>
		<station_cd1>3300116</station_cd1>
		<station_cd2>3300117</station_cd2>
		<station_name1>橋本</station_name1>
		<station_name2>樟葉</station_name2>
		<lat1>34.882042</lat1>
		<lon1>135.684251</lon1>
		<lat2>34.861977</lat2>
		<lon2>135.675352</lon2>
	</station_join>
	<station_join>
		<station_cd1>3300117</station_cd1>
		<station_cd2>3300118</station_cd2>
		<station_name1>樟葉</station_name1>
		<station_name2>牧野</station_name2>
		<lat1>34.861977</lat1>
		<lon1>135.675352</lon1>
		<lat2>34.843868</lat2>
		<lon2>135.665584</lon2>
	</station_join>
	<station_join>
		<station_cd1>3300118</station_cd1>
		<station_cd2>3300119</station_cd2>
		<station_name1>牧野</station_name1>
		<station_name2>御殿山</station_name2>
		<lat1>34.843868</lat1>
		<lon1>135.665584</lon1>
		<lat2>34.829178</lat2>
		<lon2>135.653969</lon2>
	</station_join>
	<station_join>
		<station_cd1>3300119</station_cd1>
		<station_cd2>3300120</station_cd2>
		<station_name1>御殿山</station_name1>
		<station_name2>枚方市</station_name2>
		<lat1>34.829178</lat1>
		<lon1>135.653969</lon1>
		<lat2>34.816171</lat2>
		<lon2>135.648814</lon2>
	</station_join>
	<station_join>
		<station_cd1>3300120</station_cd1>
		<station_cd2>3300121</station_cd2>
		<station_name1>枚方市</station_name1>
		<station_name2>枚方公園</station_name2>
		<lat1>34.816171</lat1>
		<lon1>135.648814</lon1>
		<lat2>34.811526</lat2>
		<lon2>135.639465</lon2>
	</station_join>
	<station_join>
		<station_cd1>3300121</station_cd1>
		<station_cd2>3300122</station_cd2>
		<station_name1>枚方公園</station_name1>
		<station_name2>光善寺</station_name2>
		<lat1>34.811526</lat1>
		<lon1>135.639465</lon1>
		<lat2>34.797745</lat2>
		<lon2>135.630124</lon2>
	</station_join>
	<station_join>
		<station_cd1>3300122</station_cd1>
		<station_cd2>3300123</station_cd2>
		<station_name1>光善寺</station_name1>
		<station_name2>香里園</station_name2>
		<lat1>34.797745</lat1>
		<lon1>135.630124</lon1>
		<lat2>34.784613</lat2>
		<lon2>135.630927</lon2>
	</station_join>
	<station_join>
		<station_cd1>3300123</station_cd1>
		<station_cd2>3300124</station_cd2>
		<station_name1>香里園</station_name1>
		<station_name2>寝屋川市</station_name2>
		<lat1>34.784613</lat1>
		<lon1>135.630927</lon1>
		<lat2>34.763893</lat2>
		<lon2>135.620603</lon2>
	</station_join>
	<station_join>
		<station_cd1>3300124</station_cd1>
		<station_cd2>3300125</station_cd2>
		<station_name1>寝屋川市</station_name1>
		<station_name2>萱島</station_name2>
		<lat1>34.763893</lat1>
		<lon1>135.620603</lon1>
		<lat2>34.747453</lat2>
		<lon2>135.61118</lon2>
	</station_join>
	<station_join>
		<station_cd1>3300125</station_cd1>
		<station_cd2>3300126</station_cd2>
		<station_name1>萱島</station_name1>
		<station_name2>大和田</station_name2>
		<lat1>34.747453</lat1>
		<lon1>135.61118</lon1>
		<lat2>34.742962</lat2>
		<lon2>135.602667</lon2>
	</station_join>
	<station_join>
		<station_cd1>3300126</station_cd1>
		<station_cd2>3300127</station_cd2>
		<station_name1>大和田</station_name1>
		<station_name2>古川橋</station_name2>
		<lat1>34.742962</lat1>
		<lon1>135.602667</lon1>
		<lat2>34.73994</lat2>
		<lon2>135.591484</lon2>
	</station_join>
	<station_join>
		<station_cd1>3300127</station_cd1>
		<station_cd2>3300128</station_cd2>
		<station_name1>古川橋</station_name1>
		<station_name2>門真市</station_name2>
		<lat1>34.73994</lat1>
		<lon1>135.591484</lon1>
		<lat2>34.73809</lat2>
		<lon2>135.583224</lon2>
	</station_join>
	<station_join>
		<station_cd1>3300128</station_cd1>
		<station_cd2>3300129</station_cd2>
		<station_name1>門真市</station_name1>
		<station_name2>西三荘</station_name2>
		<lat1>34.73809</lat1>
		<lon1>135.583224</lon1>
		<lat2>34.737309</lat2>
		<lon2>135.5759</lon2>
	</station_join>
	<station_join>
		<station_cd1>3300129</station_cd1>
		<station_cd2>3300130</station_cd2>
		<station_name1>西三荘</station_name1>
		<station_name2>守口市</station_name2>
		<lat1>34.737309</lat1>
		<lon1>135.5759</lon1>
		<lat2>34.735323</lat2>
		<lon2>135.565273</lon2>
	</station_join>
	<station_join>
		<station_cd1>3300130</station_cd1>
		<station_cd2>3300131</station_cd2>
		<station_name1>守口市</station_name1>
		<station_name2>土居</station_name2>
		<lat1>34.735323</lat1>
		<lon1>135.565273</lon1>
		<lat2>34.730577</lat2>
		<lon2>135.559763</lon2>
	</station_join>
	<station_join>
		<station_cd1>3300131</station_cd1>
		<station_cd2>3300132</station_cd2>
		<station_name1>土居</station_name1>
		<station_name2>滝井</station_name2>
		<lat1>34.730577</lat1>
		<lon1>135.559763</lon1>
		<lat2>34.727868</lat2>
		<lon2>135.557463</lon2>
	</station_join>
	<station_join>
		<station_cd1>3300132</station_cd1>
		<station_cd2>3300133</station_cd2>
		<station_name1>滝井</station_name1>
		<station_name2>千林</station_name2>
		<lat1>34.727868</lat1>
		<lon1>135.557463</lon1>
		<lat2>34.723966</lat2>
		<lon2>135.554741</lon2>
	</station_join>
	<station_join>
		<station_cd1>3300133</station_cd1>
		<station_cd2>3300134</station_cd2>
		<station_name1>千林</station_name1>
		<station_name2>森小路</station_name2>
		<lat1>34.723966</lat1>
		<lon1>135.554741</lon1>
		<lat2>34.719419</lat2>
		<lon2>135.551686</lon2>
	</station_join>
	<station_join>
		<station_cd1>3300134</station_cd1>
		<station_cd2>3300135</station_cd2>
		<station_name1>森小路</station_name1>
		<station_name2>関目</station_name2>
		<lat1>34.719419</lat1>
		<lon1>135.551686</lon1>
		<lat2>34.71252</lat2>
		<lon2>135.546953</lon2>
	</station_join>
	<station_join>
		<station_cd1>3300135</station_cd1>
		<station_cd2>3300136</station_cd2>
		<station_name1>関目</station_name1>
		<station_name2>野江</station_name2>
		<lat1>34.71252</lat1>
		<lon1>135.546953</lon1>
		<lat2>34.707223</lat2>
		<lon2>135.543356</lon2>
	</station_join>
	<station_join>
		<station_cd1>3300136</station_cd1>
		<station_cd2>3300137</station_cd2>
		<station_name1>野江</station_name1>
		<station_name2>京橋</station_name2>
		<lat1>34.707223</lat1>
		<lon1>135.543356</lon1>
		<lat2>34.697052</lat2>
		<lon2>135.532182</lon2>
	</station_join>
	<station_join>
		<station_cd1>3300137</station_cd1>
		<station_cd2>3300138</station_cd2>
		<station_name1>京橋</station_name1>
		<station_name2>天満橋</station_name2>
		<lat1>34.697052</lat1>
		<lon1>135.532182</lon1>
		<lat2>34.6902</lat2>
		<lon2>135.516633</lon2>
	</station_join>
	<station_join>
		<station_cd1>3300138</station_cd1>
		<station_cd2>3300139</station_cd2>
		<station_name1>天満橋</station_name1>
		<station_name2>北浜</station_name2>
		<lat1>34.6902</lat1>
		<lon1>135.516633</lon1>
		<lat2>34.691799</lat2>
		<lon2>135.50683</lon2>
	</station_join>
	<station_join>
		<station_cd1>3300139</station_cd1>
		<station_cd2>3300140</station_cd2>
		<station_name1>北浜</station_name1>
		<station_name2>淀屋橋</station_name2>
		<lat1>34.691799</lat1>
		<lon1>135.50683</lon1>
		<lat2>34.692456</lat2>
		<lon2>135.501648</lon2>
	</station_join>
	<station_join>
		<station_cd1>3300141</station_cd1>
		<station_cd2>3300101</station_cd2>
		<station_name1>神宮丸太町</station_name1>
		<station_name2>三条</station_name2>
		<lat1>35.017669</lat1>
		<lon1>135.772161</lon1>
		<lat2>35.009114</lat2>
		<lon2>135.772274</lon2>
	</station_join>
	<station_join>
		<station_cd1>3300142</station_cd1>
		<station_cd2>3300141</station_cd2>
		<station_name1>出町柳</station_name1>
		<station_name2>神宮丸太町</station_name2>
		<lat1>35.029613</lat1>
		<lon1>135.77244</lon1>
		<lat2>35.017669</lat2>
		<lon2>135.772161</lon2>
	</station_join>
</ekidata>
