<?xml version="1.0" encoding="UTF-8"?>
<ekidata version="ekidata.jp line api 1.0">
	<line>
		<line_cd>11916</line_cd>
		<line_name>海の中道線</line_name>
		<line_lon>130.40419308203</line_lon>
		<line_lat>33.67670942056</line_lat>
		<line_zoom>12</line_zoom>
	</line>
	<station>
		<station_cd>1191601</station_cd>
		<station_g_cd>1191601</station_g_cd>
		<station_name>西戸崎</station_name>
		<lon>130.35777</lon>
		<lat>33.650139</lat>
	</station>
	<station>
		<station_cd>1191602</station_cd>
		<station_g_cd>1191602</station_g_cd>
		<station_name>海ノ中道</station_name>
		<lon>130.361633</lon>
		<lat>33.664241</lat>
	</station>
	<station>
		<station_cd>1191603</station_cd>
		<station_g_cd>1191603</station_g_cd>
		<station_name>雁ノ巣</station_name>
		<lon>130.403312</lon>
		<lat>33.683872</lat>
	</station>
	<station>
		<station_cd>1191604</station_cd>
		<station_g_cd>1191604</station_g_cd>
		<station_name>奈多</station_name>
		<lon>130.411983</lon>
		<lat>33.68646</lat>
	</station>
	<station>
		<station_cd>1191605</station_cd>
		<station_g_cd>1191605</station_g_cd>
		<station_name>和白</station_name>
		<lon>130.429918</lon>
		<lat>33.688888</lat>
	</station>
	<station>
		<station_cd>1191606</station_cd>
		<station_g_cd>1190227</station_g_cd>
		<station_name>香椎</station_name>
		<lon>130.444063</lon>
		<lat>33.659228</lat>
	</station>
</ekidata>
