<?xml version="1.0" encoding="UTF-8"?>
<ekidata version="ekidata.jp line api 1.0">
	<line>
		<line_cd>99510</line_cd>
		<line_name>東海交通事業城北線</line_name>
		<line_lon>136.89666252116</line_lon>
		<line_lat>35.229299962293</line_lat>
		<line_zoom>13</line_zoom>
	</line>
	<station>
		<station_cd>9951001</station_cd>
		<station_g_cd>1150234</station_g_cd>
		<station_name>枇杷島</station_name>
		<lon>136.861816</lon>
		<lat>35.198681</lat>
	</station>
	<station>
		<station_cd>9951002</station_cd>
		<station_g_cd>9951002</station_g_cd>
		<station_name>尾張星の宮</station_name>
		<lon>136.855011</lon>
		<lat>35.212988</lat>
	</station>
	<station>
		<station_cd>9951003</station_cd>
		<station_g_cd>9951003</station_g_cd>
		<station_name>小田井</station_name>
		<lon>136.880491</lon>
		<lat>35.221043</lat>
	</station>
	<station>
		<station_cd>9951004</station_cd>
		<station_g_cd>9951004</station_g_cd>
		<station_name>比良</station_name>
		<lon>136.90178</lon>
		<lat>35.228549</lat>
	</station>
	<station>
		<station_cd>9951005</station_cd>
		<station_g_cd>9951005</station_g_cd>
		<station_name>味美</station_name>
		<lon>136.932263</lon>
		<lat>35.229504</lat>
	</station>
	<station>
		<station_cd>9951006</station_cd>
		<station_g_cd>1141107</station_g_cd>
		<station_name>勝川</station_name>
		<lon>136.952734</lon>
		<lat>35.227821</lat>
	</station>
</ekidata>
