<?xml version="1.0" encoding="UTF-8"?>
<ekidata version="ekidata.jp line api 1.0">
	<line>
		<line_cd>99905</line_cd>
		<line_name>福岡市営地下鉄空港線</line_name>
		<line_lon>130.38381284938</line_lon>
		<line_lat>33.593568374055</line_lat>
		<line_zoom>12</line_zoom>
	</line>
	<station>
		<station_cd>9990501</station_cd>
		<station_g_cd>9990501</station_g_cd>
		<station_name>福岡空港</station_name>
		<lon>130.448501</lon>
		<lat>33.59718</lat>
	</station>
	<station>
		<station_cd>9990502</station_cd>
		<station_g_cd>9990502</station_g_cd>
		<station_name>東比恵</station_name>
		<lon>130.43128</lon>
		<lat>33.589958</lat>
	</station>
	<station>
		<station_cd>9990503</station_cd>
		<station_g_cd>1190101</station_g_cd>
		<station_name>博多</station_name>
		<lon>130.42085</lon>
		<lat>33.590204</lat>
	</station>
	<station>
		<station_cd>9990504</station_cd>
		<station_g_cd>9990504</station_g_cd>
		<station_name>祇園</station_name>
		<lon>130.414614</lon>
		<lat>33.594124</lat>
	</station>
	<station>
		<station_cd>9990505</station_cd>
		<station_g_cd>9990505</station_g_cd>
		<station_name>中洲川端</station_name>
		<lon>130.406418</lon>
		<lat>33.594749</lat>
	</station>
	<station>
		<station_cd>9990506</station_cd>
		<station_g_cd>9990506</station_g_cd>
		<station_name>天神</station_name>
		<lon>130.39906</lon>
		<lat>33.591346</lat>
	</station>
	<station>
		<station_cd>9990507</station_cd>
		<station_g_cd>9990507</station_g_cd>
		<station_name>赤坂</station_name>
		<lon>130.391005</lon>
		<lat>33.589124</lat>
	</station>
	<station>
		<station_cd>9990508</station_cd>
		<station_g_cd>9990508</station_g_cd>
		<station_name>大濠公園</station_name>
		<lon>130.378784</lon>
		<lat>33.589957</lat>
	</station>
	<station>
		<station_cd>9990509</station_cd>
		<station_g_cd>9990509</station_g_cd>
		<station_name>唐人町</station_name>
		<lon>130.370451</lon>
		<lat>33.590235</lat>
	</station>
	<station>
		<station_cd>9990510</station_cd>
		<station_g_cd>9990510</station_g_cd>
		<station_name>西新</station_name>
		<lon>130.359619</lon>
		<lat>33.583846</lat>
	</station>
	<station>
		<station_cd>9990511</station_cd>
		<station_g_cd>9990511</station_g_cd>
		<station_name>藤崎</station_name>
		<lon>130.348231</lon>
		<lat>33.581347</lat>
	</station>
	<station>
		<station_cd>9990512</station_cd>
		<station_g_cd>9990512</station_g_cd>
		<station_name>室見</station_name>
		<lon>130.340176</lon>
		<lat>33.581069</lat>
	</station>
	<station>
		<station_cd>9990513</station_cd>
		<station_g_cd>1190901</station_g_cd>
		<station_name>姪浜</station_name>
		<lon>130.32521</lon>
		<lat>33.583764</lat>
	</station>
</ekidata>
