<?xml version="1.0" encoding="UTF-8"?>
<ekidata version="ekidata.jp station api 1.0">
	<station>
		<line_cd>99213</line_cd>
		<line_name>阿武隈急行線</line_name>
		<station_cd>9921312</station_cd>
		<station_g_cd>9921312</station_g_cd>
		<station_name>梁川</station_name>
		<lon>140.603279</lon>
		<lat>37.845815</lat>
	</station>
	<station_g>
		<pref_cd>7</pref_cd>
		<line_cd>99213</line_cd>
		<line_name>阿武隈急行線</line_name>
		<station_cd>9921312</station_cd>
		<station_name>梁川</station_name>
	</station_g>
</ekidata>
