{"station_g":[{"pref_cd":16,"line_cd":11416,"line_name":"JR高山本線","station_cd":1141644,"station_name":"富山"},{"pref_cd":16,"line_cd":99408,"line_name":"富山地鉄本線","station_cd":9940801,"station_name":"電鉄富山"},{"pref_cd":16,"line_cd":99410,"line_name":"富山地鉄不二越・上滝線","station_cd":9941001,"station_name":"電鉄富山"},{"pref_cd":16,"line_cd":99422,"line_name":"富山地鉄富山都心線【３系統(環状線)】","station_cd":9942211,"station_name":"電鉄富山駅・エスタ前"},{"pref_cd":16,"line_cd":99422,"line_name":"富山地鉄富山都心線【３系統(環状線)】","station_cd":9942214,"station_name":"富山駅"},{"pref_cd":16,"line_cd":99413,"line_name":"富山地鉄市内線【１・２系統】","station_cd":9941313,"station_name":"電鉄富山駅・エスタ前"},{"pref_cd":16,"line_cd":99413,"line_name":"富山地鉄市内線【１・２系統】","station_cd":9941322,"station_name":"富山駅"},{"pref_cd":16,"line_cd":99415,"line_name":"富山港線","station_cd":9941501,"station_name":"富山駅"},{"pref_cd":16,"line_cd":99425,"line_name":"あいの風とやま鉄道線","station_cd":1141555,"station_name":"富山"}]}
