<?xml version="1.0" encoding="UTF-8"?>
<ekidata version="ekidata.jp station api 1.0">
	<station>
		<line_cd>99805</line_cd>
		<line_name>伊予鉄道郡中線</line_name>
		<station_cd>9980504</station_cd>
		<station_g_cd>9980504</station_g_cd>
		<station_name>余戸</station_name>
		<lon>132.733887</lon>
		<lat>33.816173</lat>
	</station>
	<station_g>
		<pref_cd>38</pref_cd>
		<line_cd>99805</line_cd>
		<line_name>伊予鉄道郡中線</line_name>
		<station_cd>9980504</station_cd>
		<station_name>余戸</station_name>
	</station_g>
</ekidata>
