<?xml version="1.0" encoding="UTF-8"?>
<ekidata version="ekidata.jp station api 1.0">
	<station>
		<line_cd>99922</line_cd>
		<line_name>熊本市電Ａ系統</line_name>
		<station_cd>9992203</station_cd>
		<station_g_cd>1190341</station_g_cd>
		<station_name>熊本駅前</station_name>
		<lon>130.690398</lon>
		<lat>32.790377</lat>
	</station>
	<station_g>
		<pref_cd>43</pref_cd>
		<line_cd>11903</line_cd>
		<line_name>JR鹿児島本線(博多～八代)</line_name>
		<station_cd>1190341</station_cd>
		<station_name>熊本</station_name>
	</station_g>
	<station_g>
		<pref_cd>43</pref_cd>
		<line_cd>11923</line_cd>
		<line_name>阿蘇高原線</line_name>
		<station_cd>1192301</station_cd>
		<station_name>熊本</station_name>
	</station_g>
	<station_g>
		<pref_cd>43</pref_cd>
		<line_cd>11924</line_cd>
		<line_name>三角線（あまくさみすみ線）</line_name>
		<station_cd>1192401</station_cd>
		<station_name>熊本</station_name>
	</station_g>
	<station_g>
		<pref_cd>43</pref_cd>
		<line_cd>99922</line_cd>
		<line_name>熊本市電Ａ系統</line_name>
		<station_cd>9992203</station_cd>
		<station_name>熊本駅前</station_name>
	</station_g>
</ekidata>
