<?xml version="1.0" encoding="UTF-8"?>
<ekidata version="ekidata.jp station api 1.0">
	<station>
		<line_cd>99206</line_cd>
		<line_name>青い森鉄道線</line_name>
		<station_cd>1120118</station_cd>
		<station_g_cd>1120118</station_g_cd>
		<station_name>小柳</station_name>
		<lon>140.798149</lon>
		<lat>40.818223</lat>
	</station>
	<station_g>
		<pref_cd>2</pref_cd>
		<line_cd>99206</line_cd>
		<line_name>青い森鉄道線</line_name>
		<station_cd>1120118</station_cd>
		<station_name>小柳</station_name>
	</station_g>
</ekidata>
