<?xml version="1.0" encoding="UTF-8"?>
<ekidata version="ekidata.jp station api 1.0">
	<station>
		<line_cd>21002</line_cd>
		<line_name>東武伊勢崎線</line_name>
		<station_cd>2100230</station_cd>
		<station_g_cd>2100230</station_g_cd>
		<station_name>東武動物公園</station_name>
		<lon>139.726901</lon>
		<lat>36.024604</lat>
	</station>
	<station_g>
		<pref_cd>11</pref_cd>
		<line_cd>21002</line_cd>
		<line_name>東武伊勢崎線</line_name>
		<station_cd>2100230</station_cd>
		<station_name>東武動物公園</station_name>
	</station_g>
	<station_g>
		<pref_cd>11</pref_cd>
		<line_cd>21003</line_cd>
		<line_name>東武日光線</line_name>
		<station_cd>2100301</station_cd>
		<station_name>東武動物公園</station_name>
	</station_g>
</ekidata>
