<?xml version="1.0" encoding="UTF-8"?>
<ekidata version="ekidata.jp station_join api 1.0">
	<station_join>
		<station_cd1>9970401</station_cd1>
		<station_cd2>9970402</station_cd2>
		<station_name1>倉敷市</station_name1>
		<station_name2>球場前</station_name2>
		<lat1>34.601595</lat1>
		<lon1>133.765512</lon1>
		<lat2>34.591143</lat2>
		<lon2>133.747177</lon2>
	</station_join>
	<station_join>
		<station_cd1>9970402</station_cd1>
		<station_cd2>9970403</station_cd2>
		<station_name1>球場前</station_name1>
		<station_name2>西富井</station_name2>
		<lat1>34.591143</lat1>
		<lon1>133.747177</lon1>
		<lat2>34.577809</lat2>
		<lon2>133.743361</lon2>
	</station_join>
	<station_join>
		<station_cd1>9970403</station_cd1>
		<station_cd2>9970404</station_cd2>
		<station_name1>西富井</station_name1>
		<station_name2>福井</station_name2>
		<lat1>34.577809</lat1>
		<lon1>133.743361</lon1>
		<lat2>34.569804</lat2>
		<lon2>133.744495</lon2>
	</station_join>
	<station_join>
		<station_cd1>9970404</station_cd1>
		<station_cd2>9970405</station_cd2>
		<station_name1>福井</station_name1>
		<station_name2>浦田</station_name2>
		<lat1>34.569804</lat1>
		<lon1>133.744495</lon1>
		<lat2>34.561271</lat2>
		<lon2>133.749761</lon2>
	</station_join>
	<station_join>
		<station_cd1>9970405</station_cd1>
		<station_cd2>9970406</station_cd2>
		<station_name1>浦田</station_name1>
		<station_name2>弥生</station_name2>
		<lat1>34.561271</lat1>
		<lon1>133.749761</lon1>
		<lat2>34.544359</lat2>
		<lon2>133.747534</lon2>
	</station_join>
	<station_join>
		<station_cd1>9970406</station_cd1>
		<station_cd2>9970407</station_cd2>
		<station_name1>弥生</station_name1>
		<station_name2>栄</station_name2>
		<lat1>34.544359</lat1>
		<lon1>133.747534</lon1>
		<lat2>34.53791</lat2>
		<lon2>133.744915</lon2>
	</station_join>
	<station_join>
		<station_cd1>9970407</station_cd1>
		<station_cd2>9970408</station_cd2>
		<station_name1>栄</station_name1>
		<station_name2>常盤</station_name2>
		<lat1>34.53791</lat1>
		<lon1>133.744915</lon1>
		<lat2>34.53401</lat2>
		<lon2>133.743246</lon2>
	</station_join>
	<station_join>
		<station_cd1>9970408</station_cd1>
		<station_cd2>9970409</station_cd2>
		<station_name1>常盤</station_name1>
		<station_name2>水島</station_name2>
		<lat1>34.53401</lat1>
		<lon1>133.743246</lon1>
		<lat2>34.529169</lat2>
		<lon2>133.741235</lon2>
	</station_join>
	<station_join>
		<station_cd1>9970409</station_cd1>
		<station_cd2>9970410</station_cd2>
		<station_name1>水島</station_name1>
		<station_name2>三菱自工前</station_name2>
		<lat1>34.529169</lat1>
		<lon1>133.741235</lon1>
		<lat2>34.522906</lat2>
		<lon2>133.734197</lon2>
	</station_join>
</ekidata>
